{
  "$schema": "https://ui.shadcn.com/schema/registry-item.json",
  "name": "glowing-dot-grid",
  "title": "Glowing Dot Grid",
  "description": "An interactive grid of dots that glow and expand on hover with beautiful proximity-based effects. Perfect for hero sections and interactive backgrounds. Nyxhora UI",
  "registryDependencies": [],
  "files": [
    {
      "path": "registry/ui/glowing-dot-grid.tsx",
      "content": "\"use client\";\r\n\r\nimport { memo, useMemo, useRef, useState, useEffect } from \"react\";\r\nimport { cn } from \"@/lib/utils\";\r\n\r\nexport interface GlowingDotGridProps {\r\n    /** Number of columns in the grid */\r\n    columns?: number;\r\n    /** Number of rows in the grid */\r\n    rows?: number;\r\n    /** Base dot color */\r\n    dotColor?: string;\r\n    /** Dot size in pixels */\r\n    dotSize?: number;\r\n    /** Gap between dots in rem */\r\n    gap?: number;\r\n    /** Hover effect size multiplier */\r\n    hoverScale?: number;\r\n    /** Effect radius (how many dots are affected) */\r\n    effectRadius?: number;\r\n    /** Background gradient start color */\r\n    gradientStart?: string;\r\n    /** Background gradient end color */\r\n    gradientEnd?: string;\r\n    /** Whether to show corner shadow/vignette */\r\n    showVignette?: boolean;\r\n    /** Additional CSS classes */\r\n    className?: string;\r\n    /** Children content to display over the grid */\r\n    children?: React.ReactNode;\r\n}\r\n\r\nconst GlowingDotGrid = memo(\r\n    ({\r\n        columns = 12,\r\n        rows = 8,\r\n        dotColor = \"#A9C9FF\",\r\n        dotSize = 4,\r\n        gap = 2,\r\n        hoverScale = 12,\r\n        effectRadius = 100,\r\n        gradientStart = \"#0a0a0a\",\r\n        gradientEnd = \"#0a0a0a\",\r\n        showVignette = true,\r\n        className,\r\n        children,\r\n    }: GlowingDotGridProps) => {\r\n        const containerRef = useRef<HTMLDivElement>(null);\r\n        const [mousePos, setMousePos] = useState<{ x: number; y: number } | null>(null);\r\n\r\n        // Generate tiles array\r\n        const tiles = useMemo(() => {\r\n            return Array.from({ length: columns * rows }, (_, i) => i);\r\n        }, [columns, rows]);\r\n\r\n        // Track mouse position relative to the container\r\n        useEffect(() => {\r\n            const container = containerRef.current;\r\n            if (!container) return;\r\n\r\n            const handleMouseMove = (e: MouseEvent) => {\r\n                const rect = container.getBoundingClientRect();\r\n                setMousePos({\r\n                    x: e.clientX - rect.left,\r\n                    y: e.clientY - rect.top,\r\n                });\r\n            };\r\n\r\n            const handleMouseLeave = () => {\r\n                setMousePos(null);\r\n            };\r\n\r\n            container.addEventListener(\"mousemove\", handleMouseMove);\r\n            container.addEventListener(\"mouseleave\", handleMouseLeave);\r\n\r\n            return () => {\r\n                container.removeEventListener(\"mousemove\", handleMouseMove);\r\n                container.removeEventListener(\"mouseleave\", handleMouseLeave);\r\n            };\r\n        }, []);\r\n\r\n        return (\r\n            <div\r\n                ref={containerRef}\r\n                className={cn(\r\n                    \"relative w-full h-full overflow-hidden\",\r\n                    className\r\n                )}\r\n                style={{\r\n                    background: `linear-gradient(180deg, ${gradientStart} 0%, ${gradientEnd} 100%)`,\r\n                }}\r\n            >\r\n                {/* Grid container - z-0 */}\r\n                <div\r\n                    className=\"absolute inset-0 grid z-0\"\r\n                    style={{\r\n                        gridTemplateColumns: `repeat(${columns}, 1fr)`,\r\n                        gridTemplateRows: `repeat(${rows}, 1fr)`,\r\n                    }}\r\n                >\r\n                    {tiles.map((index) => {\r\n                        const col = index % columns;\r\n                        const row = Math.floor(index / columns);\r\n\r\n                        return (\r\n                            <DotTile\r\n                                key={index}\r\n                                col={col}\r\n                                row={row}\r\n                                columns={columns}\r\n                                rows={rows}\r\n                                dotColor={dotColor}\r\n                                dotSize={dotSize}\r\n                                hoverScale={hoverScale}\r\n                                effectRadius={effectRadius}\r\n                                mousePos={mousePos}\r\n                            />\r\n                        );\r\n                    })}\r\n                </div>\r\n\r\n                {/* Content overlay - z-10 */}\r\n                {children && (\r\n                    <div className=\"absolute inset-0 z-10 flex items-center justify-center pointer-events-none\">\r\n                        <div className=\"pointer-events-auto\">\r\n                            {children}\r\n                        </div>\r\n                    </div>\r\n                )}\r\n\r\n                {/* Vignette overlay - z-20, purely visual */}\r\n                {showVignette && (\r\n                    <div\r\n                        className=\"absolute inset-0 pointer-events-none z-20\"\r\n                        style={{\r\n                            background: `\r\n                radial-gradient(ellipse at top left, rgba(0,0,0,0.6) 0%, transparent 35%),\r\n                radial-gradient(ellipse at top right, rgba(0,0,0,0.6) 0%, transparent 35%),\r\n                radial-gradient(ellipse at bottom left, rgba(0,0,0,0.6) 0%, transparent 35%),\r\n                radial-gradient(ellipse at bottom right, rgba(0,0,0,0.6) 0%, transparent 35%)\r\n              `,\r\n                        }}\r\n                    />\r\n                )}\r\n            </div>\r\n        );\r\n    }\r\n);\r\n\r\n// Individual dot tile component for better performance\r\nconst DotTile = memo(({\r\n    col,\r\n    row,\r\n    columns,\r\n    rows,\r\n    dotColor,\r\n    dotSize,\r\n    hoverScale,\r\n    effectRadius,\r\n    mousePos,\r\n}: {\r\n    col: number;\r\n    row: number;\r\n    columns: number;\r\n    rows: number;\r\n    dotColor: string;\r\n    dotSize: number;\r\n    hoverScale: number;\r\n    effectRadius: number;\r\n    mousePos: { x: number; y: number } | null;\r\n}) => {\r\n    const tileRef = useRef<HTMLDivElement>(null);\r\n\r\n    // Calculate the intensity based on distance from mouse\r\n    const getIntensity = () => {\r\n        if (!mousePos || !tileRef.current) return 0;\r\n\r\n        const rect = tileRef.current.getBoundingClientRect();\r\n        const parent = tileRef.current.parentElement?.parentElement;\r\n        if (!parent) return 0;\r\n\r\n        const parentRect = parent.getBoundingClientRect();\r\n\r\n        // Get the center of this tile relative to the parent\r\n        const tileCenterX = rect.left - parentRect.left + rect.width / 2;\r\n        const tileCenterY = rect.top - parentRect.top + rect.height / 2;\r\n\r\n        // Calculate distance from mouse to tile center\r\n        const distance = Math.sqrt(\r\n            Math.pow(mousePos.x - tileCenterX, 2) +\r\n            Math.pow(mousePos.y - tileCenterY, 2)\r\n        );\r\n\r\n        // Calculate intensity (1 at mouse position, 0 at effectRadius)\r\n        if (distance > effectRadius) return 0;\r\n        return Math.pow(1 - distance / effectRadius, 2); // Quadratic falloff for smoother effect\r\n    };\r\n\r\n    const intensity = getIntensity();\r\n    const scale = 1 + intensity * (hoverScale / dotSize);\r\n    const glowSize = intensity * hoverScale;\r\n\r\n    return (\r\n        <div\r\n            ref={tileRef}\r\n            className=\"flex items-center justify-center\"\r\n        >\r\n            <div\r\n                className=\"rounded-full\"\r\n                style={{\r\n                    width: `${dotSize}px`,\r\n                    height: `${dotSize}px`,\r\n                    backgroundColor: dotColor,\r\n                    boxShadow: intensity > 0\r\n                        ? `0 0 ${glowSize}px ${glowSize * 0.6}px ${dotColor}`\r\n                        : 'none',\r\n                    transform: `scale(${scale})`,\r\n                    opacity: mousePos === null ? 0.5 : intensity > 0 ? 0.5 + intensity * 0.5 : 0.25,\r\n                    transition: 'transform 100ms ease-out, box-shadow 100ms ease-out, opacity 200ms ease-out',\r\n                }}\r\n            />\r\n        </div>\r\n    );\r\n});\r\n\r\nDotTile.displayName = \"DotTile\";\r\nGlowingDotGrid.displayName = \"GlowingDotGrid\";\r\n\r\nexport { GlowingDotGrid };\r\n",
      "type": "registry:ui"
    }
  ],
  "type": "registry:ui"
}